{
    "response": {
        "version": "0.1", 
        "uri": "http://api.wunderground.com/api/a0291ba2d850ab86/conditions/forecast/hourly/q/Finland/Nousiainen.json", 
        "termsofService": "http://www.wunderground.com/weather/api/d/terms.html", 
        "features": {
            "hourly": 1
        }
    }, 
    "hourly_forecast": [
        {
            "FCTTIME": {
                "hour": "13", 
                "hour_padded": "13", 
                "min": "00", 
                "min_unpadded": "0", 
                "sec": "0", 
                "year": "2017", 
                "mon": "11", 
                "mon_padded": "11", 
                "mon_abbrev": "Nov", 
                "mday": "10", 
                "mday_padded": "10", 
                "yday": "313", 
                "isdst": "0", 
                "epoch": "1510311600", 
                "pretty": "1:00 PM EET on November 10, 2017", 
                "civil": "1:00 PM", 
                "month_name": "November", 
                "month_name_abbrev": "Nov", 
                "weekday_name": "Friday", 
                "weekday_name_night": "Friday Night", 
                "weekday_name_abbrev": "Fri", 
                "weekday_name_unlang": "Friday", 
                "weekday_name_night_unlang": "Friday Night", 
                "ampm": "PM", 
                "tz": "", 
                "age": "", 
                "UTCDATE": ""
            }, 
            "temp": {
                "english": "44", 
                "metric": "7"
            }, 
            "dewpoint": {
                "english": "37", 
                "metric": "3"
            }, 
            "condition": "Partly Cloudy", 
            "icon": "partlycloudy", 
            "icon_url": "http://icons.wxug.com/i/c/k/partlycloudy.gif", 
            "fctcode": "2", 
            "sky": "55", 
            "wspd": {
                "english": "11", 
                "metric": "18"
            }, 
            "wdir": {
                "dir": "SW", 
                "degrees": "222"
            }, 
            "wx": "Partly Cloudy", 
            "uvi": "0", 
            "humidity": "76", 
            "windchill": {
                "english": "39", 
                "metric": "4"
            }, 
            "heatindex": {
                "english": "-9999", 
                "metric": "-9999"
            }, 
            "feelslike": {
                "english": "39", 
                "metric": "4"
            }, 
            "qpf": {
                "english": "0.0", 
                "metric": "0"
            }, 
            "snow": {
                "english": "0.0", 
                "metric": "0"
            }, 
            "pop": "0", 
            "mslp": {
                "english": "29.47", 
                "metric": "998"
            }
        }, 
        {
            "FCTTIME": {
                "hour": "14", 
                "hour_padded": "14", 
                "min": "00", 
                "min_unpadded": "0", 
                "sec": "0", 
                "year": "2017", 
                "mon": "11", 
                "mon_padded": "11", 
                "mon_abbrev": "Nov", 
                "mday": "10", 
                "mday_padded": "10", 
                "yday": "313", 
                "isdst": "0", 
                "epoch": "1510315200", 
                "pretty": "2:00 PM EET on November 10, 2017", 
                "civil": "2:00 PM", 
                "month_name": "November", 
                "month_name_abbrev": "Nov", 
                "weekday_name": "Friday", 
                "weekday_name_night": "Friday Night", 
                "weekday_name_abbrev": "Fri", 
                "weekday_name_unlang": "Friday", 
                "weekday_name_night_unlang": "Friday Night", 
                "ampm": "PM", 
                "tz": "", 
                "age": "", 
                "UTCDATE": ""
            }, 
            "temp": {
                "english": "44", 
                "metric": "7"
            }, 
            "dewpoint": {
                "english": "37", 
                "metric": "3"
            }, 
            "condition": "Mostly Cloudy", 
            "icon": "mostlycloudy", 
            "icon_url": "http://icons.wxug.com/i/c/k/mostlycloudy.gif", 
            "fctcode": "3", 
            "sky": "60", 
            "wspd": {
                "english": "10", 
                "metric": "16"
            }, 
            "wdir": {
                "dir": "SW", 
                "degrees": "215"
            }, 
            "wx": "Mostly Cloudy", 
            "uvi": "0", 
            "humidity": "74", 
            "windchill": {
                "english": "39", 
                "metric": "4"
            }, 
            "heatindex": {
                "english": "-9999", 
                "metric": "-9999"
            }, 
            "feelslike": {
                "english": "39", 
                "metric": "4"
            }, 
            "qpf": {
                "english": "0.0", 
                "metric": "0"
            }, 
            "snow": {
                "english": "0.0", 
                "metric": "0"
            }, 
            "pop": "0", 
            "mslp": {
                "english": "29.46", 
                "metric": "998"
            }
        }, 
        {
            "FCTTIME": {
                "hour": "15", 
                "hour_padded": "15", 
                "min": "00", 
                "min_unpadded": "0", 
                "sec": "0", 
                "year": "2017", 
                "mon": "11", 
                "mon_padded": "11", 
                "mon_abbrev": "Nov", 
                "mday": "10", 
                "mday_padded": "10", 
                "yday": "313", 
                "isdst": "0", 
                "epoch": "1510318800", 
                "pretty": "3:00 PM EET on November 10, 2017", 
                "civil": "3:00 PM", 
                "month_name": "November", 
                "month_name_abbrev": "Nov", 
                "weekday_name": "Friday", 
                "weekday_name_night": "Friday Night", 
                "weekday_name_abbrev": "Fri", 
                "weekday_name_unlang": "Friday", 
                "weekday_name_night_unlang": "Friday Night", 
                "ampm": "PM", 
                "tz": "", 
                "age": "", 
                "UTCDATE": ""
            }, 
            "temp": {
                "english": "43", 
                "metric": "6"
            }, 
            "dewpoint": {
                "english": "36", 
                "metric": "2"
            }, 
            "condition": "Mostly Cloudy", 
            "icon": "mostlycloudy", 
            "icon_url": "http://icons.wxug.com/i/c/k/mostlycloudy.gif", 
            "fctcode": "3", 
            "sky": "69", 
            "wspd": {
                "english": "9", 
                "metric": "14"
            }, 
            "wdir": {
                "dir": "SSW", 
                "degrees": "208"
            }, 
            "wx": "Mostly Cloudy", 
            "uvi": "0", 
            "humidity": "76", 
            "windchill": {
                "english": "38", 
                "metric": "3"
            }, 
            "heatindex": {
                "english": "-9999", 
                "metric": "-9999"
            }, 
            "feelslike": {
                "english": "38", 
                "metric": "3"
            }, 
            "qpf": {
                "english": "0.0", 
                "metric": "0"
            }, 
            "snow": {
                "english": "0.0", 
                "metric": "0"
            }, 
            "pop": "0", 
            "mslp": {
                "english": "29.45", 
                "metric": "997"
            }
        }, 
        {
            "FCTTIME": {
                "hour": "16", 
                "hour_padded": "16", 
                "min": "00", 
                "min_unpadded": "0", 
                "sec": "0", 
                "year": "2017", 
                "mon": "11", 
                "mon_padded": "11", 
                "mon_abbrev": "Nov", 
                "mday": "10", 
                "mday_padded": "10", 
                "yday": "313", 
                "isdst": "0", 
                "epoch": "1510322400", 
                "pretty": "4:00 PM EET on November 10, 2017", 
                "civil": "4:00 PM", 
                "month_name": "November", 
                "month_name_abbrev": "Nov", 
                "weekday_name": "Friday", 
                "weekday_name_night": "Friday Night", 
                "weekday_name_abbrev": "Fri", 
                "weekday_name_unlang": "Friday", 
                "weekday_name_night_unlang": "Friday Night", 
                "ampm": "PM", 
                "tz": "", 
                "age": "", 
                "UTCDATE": ""
            }, 
            "temp": {
                "english": "42", 
                "metric": "6"
            }, 
            "dewpoint": {
                "english": "36", 
                "metric": "2"
            }, 
            "condition": "Overcast", 
            "icon": "cloudy", 
            "icon_url": "http://icons.wxug.com/i/c/k/cloudy.gif", 
            "fctcode": "4", 
            "sky": "83", 
            "wspd": {
                "english": "9", 
                "metric": "14"
            }, 
            "wdir": {
                "dir": "SSW", 
                "degrees": "200"
            }, 
            "wx": "Cloudy", 
            "uvi": "0", 
            "humidity": "79", 
            "windchill": {
                "english": "38", 
                "metric": "3"
            }, 
            "heatindex": {
                "english": "-9999", 
                "metric": "-9999"
            }, 
            "feelslike": {
                "english": "38", 
                "metric": "3"
            }, 
            "qpf": {
                "english": "0.0", 
                "metric": "0"
            }, 
            "snow": {
                "english": "0.0", 
                "metric": "0"
            }, 
            "pop": "0", 
            "mslp": {
                "english": "29.45", 
                "metric": "997"
            }
        }, 
        {
            "FCTTIME": {
                "hour": "17", 
                "hour_padded": "17", 
                "min": "00", 
                "min_unpadded": "0", 
                "sec": "0", 
                "year": "2017", 
                "mon": "11", 
                "mon_padded": "11", 
                "mon_abbrev": "Nov", 
                "mday": "10", 
                "mday_padded": "10", 
                "yday": "313", 
                "isdst": "0", 
                "epoch": "1510326000", 
                "pretty": "5:00 PM EET on November 10, 2017", 
                "civil": "5:00 PM", 
                "month_name": "November", 
                "month_name_abbrev": "Nov", 
                "weekday_name": "Friday", 
                "weekday_name_night": "Friday Night", 
                "weekday_name_abbrev": "Fri", 
                "weekday_name_unlang": "Friday", 
                "weekday_name_night_unlang": "Friday Night", 
                "ampm": "PM", 
                "tz": "", 
                "age": "", 
                "UTCDATE": ""
            }, 
            "temp": {
                "english": "41", 
                "metric": "5"
            }, 
            "dewpoint": {
                "english": "37", 
                "metric": "3"
            }, 
            "condition": "Mostly Cloudy", 
            "icon": "mostlycloudy", 
            "icon_url": "http://icons.wxug.com/i/c/k/nt_mostlycloudy.gif", 
            "fctcode": "3", 
            "sky": "73", 
            "wspd": {
                "english": "7", 
                "metric": "11"
            }, 
            "wdir": {
                "dir": "SSW", 
                "degrees": "200"
            }, 
            "wx": "Mostly Cloudy", 
            "uvi": "0", 
            "humidity": "84", 
            "windchill": {
                "english": "36", 
                "metric": "2"
            }, 
            "heatindex": {
                "english": "-9999", 
                "metric": "-9999"
            }, 
            "feelslike": {
                "english": "36", 
                "metric": "2"
            }, 
            "qpf": {
                "english": "0.0", 
                "metric": "0"
            }, 
            "snow": {
                "english": "0.0", 
                "metric": "0"
            }, 
            "pop": "1", 
            "mslp": {
                "english": "29.45", 
                "metric": "997"
            }
        }, 
        {
            "FCTTIME": {
                "hour": "18", 
                "hour_padded": "18", 
                "min": "00", 
                "min_unpadded": "0", 
                "sec": "0", 
                "year": "2017", 
                "mon": "11", 
                "mon_padded": "11", 
                "mon_abbrev": "Nov", 
                "mday": "10", 
                "mday_padded": "10", 
                "yday": "313", 
                "isdst": "0", 
                "epoch": "1510329600", 
                "pretty": "6:00 PM EET on November 10, 2017", 
                "civil": "6:00 PM", 
                "month_name": "November", 
                "month_name_abbrev": "Nov", 
                "weekday_name": "Friday", 
                "weekday_name_night": "Friday Night", 
                "weekday_name_abbrev": "Fri", 
                "weekday_name_unlang": "Friday", 
                "weekday_name_night_unlang": "Friday Night", 
                "ampm": "PM", 
                "tz": "", 
                "age": "", 
                "UTCDATE": ""
            }, 
            "temp": {
                "english": "41", 
                "metric": "5"
            }, 
            "dewpoint": {
                "english": "37", 
                "metric": "3"
            }, 
            "condition": "Mostly Cloudy", 
            "icon": "mostlycloudy", 
            "icon_url": "http://icons.wxug.com/i/c/k/nt_mostlycloudy.gif", 
            "fctcode": "3", 
            "sky": "73", 
            "wspd": {
                "english": "7", 
                "metric": "11"
            }, 
            "wdir": {
                "dir": "SSW", 
                "degrees": "193"
            }, 
            "wx": "Mostly Cloudy", 
            "uvi": "0", 
            "humidity": "86", 
            "windchill": {
                "english": "36", 
                "metric": "2"
            }, 
            "heatindex": {
                "english": "-9999", 
                "metric": "-9999"
            }, 
            "feelslike": {
                "english": "36", 
                "metric": "2"
            }, 
            "qpf": {
                "english": "0.0", 
                "metric": "0"
            }, 
            "snow": {
                "english": "0.0", 
                "metric": "0"
            }, 
            "pop": "5", 
            "mslp": {
                "english": "29.44", 
                "metric": "997"
            }
        }, 
        {
            "FCTTIME": {
                "hour": "19", 
                "hour_padded": "19", 
                "min": "00", 
                "min_unpadded": "0", 
                "sec": "0", 
                "year": "2017", 
                "mon": "11", 
                "mon_padded": "11", 
                "mon_abbrev": "Nov", 
                "mday": "10", 
                "mday_padded": "10", 
                "yday": "313", 
                "isdst": "0", 
                "epoch": "1510333200", 
                "pretty": "7:00 PM EET on November 10, 2017", 
                "civil": "7:00 PM", 
                "month_name": "November", 
                "month_name_abbrev": "Nov", 
                "weekday_name": "Friday", 
                "weekday_name_night": "Friday Night", 
                "weekday_name_abbrev": "Fri", 
                "weekday_name_unlang": "Friday", 
                "weekday_name_night_unlang": "Friday Night", 
                "ampm": "PM", 
                "tz": "", 
                "age": "", 
                "UTCDATE": ""
            }, 
            "temp": {
                "english": "41", 
                "metric": "5"
            }, 
            "dewpoint": {
                "english": "37", 
                "metric": "3"
            }, 
            "condition": "Mostly Cloudy", 
            "icon": "mostlycloudy", 
            "icon_url": "http://icons.wxug.com/i/c/k/nt_mostlycloudy.gif", 
            "fctcode": "3", 
            "sky": "68", 
            "wspd": {
                "english": "5", 
                "metric": "8"
            }, 
            "wdir": {
                "dir": "S", 
                "degrees": "175"
            }, 
            "wx": "Mostly Cloudy", 
            "uvi": "0", 
            "humidity": "87", 
            "windchill": {
                "english": "38", 
                "metric": "3"
            }, 
            "heatindex": {
                "english": "-9999", 
                "metric": "-9999"
            }, 
            "feelslike": {
                "english": "38", 
                "metric": "3"
            }, 
            "qpf": {
                "english": "0.0", 
                "metric": "0"
            }, 
            "snow": {
                "english": "0.0", 
                "metric": "0"
            }, 
            "pop": "19", 
            "mslp": {
                "english": "29.43", 
                "metric": "997"
            }
        }, 
        {
            "FCTTIME": {
                "hour": "20", 
                "hour_padded": "20", 
                "min": "00", 
                "min_unpadded": "0", 
                "sec": "0", 
                "year": "2017", 
                "mon": "11", 
                "mon_padded": "11", 
                "mon_abbrev": "Nov", 
                "mday": "10", 
                "mday_padded": "10", 
                "yday": "313", 
                "isdst": "0", 
                "epoch": "1510336800", 
                "pretty": "8:00 PM EET on November 10, 2017", 
                "civil": "8:00 PM", 
                "month_name": "November", 
                "month_name_abbrev": "Nov", 
                "weekday_name": "Friday", 
                "weekday_name_night": "Friday Night", 
                "weekday_name_abbrev": "Fri", 
                "weekday_name_unlang": "Friday", 
                "weekday_name_night_unlang": "Friday Night", 
                "ampm": "PM", 
                "tz": "", 
                "age": "", 
                "UTCDATE": ""
            }, 
            "temp": {
                "english": "40", 
                "metric": "4"
            }, 
            "dewpoint": {
                "english": "37", 
                "metric": "3"
            }, 
            "condition": "Mostly Cloudy", 
            "icon": "mostlycloudy", 
            "icon_url": "http://icons.wxug.com/i/c/k/nt_mostlycloudy.gif", 
            "fctcode": "3", 
            "sky": "68", 
            "wspd": {
                "english": "4", 
                "metric": "6"
            }, 
            "wdir": {
                "dir": "SSE", 
                "degrees": "165"
            }, 
            "wx": "Mostly Cloudy", 
            "uvi": "0", 
            "humidity": "89", 
            "windchill": {
                "english": "36", 
                "metric": "2"
            }, 
            "heatindex": {
                "english": "-9999", 
                "metric": "-9999"
            }, 
            "feelslike": {
                "english": "36", 
                "metric": "2"
            }, 
            "qpf": {
                "english": "0.0", 
                "metric": "0"
            }, 
            "snow": {
                "english": "0.0", 
                "metric": "0"
            }, 
            "pop": "24", 
            "mslp": {
                "english": "29.42", 
                "metric": "996"
            }
        }, 
        {
            "FCTTIME": {
                "hour": "21", 
                "hour_padded": "21", 
                "min": "00", 
                "min_unpadded": "0", 
                "sec": "0", 
                "year": "2017", 
                "mon": "11", 
                "mon_padded": "11", 
                "mon_abbrev": "Nov", 
                "mday": "10", 
                "mday_padded": "10", 
                "yday": "313", 
                "isdst": "0", 
                "epoch": "1510340400", 
                "pretty": "9:00 PM EET on November 10, 2017", 
                "civil": "9:00 PM", 
                "month_name": "November", 
                "month_name_abbrev": "Nov", 
                "weekday_name": "Friday", 
                "weekday_name_night": "Friday Night", 
                "weekday_name_abbrev": "Fri", 
                "weekday_name_unlang": "Friday", 
                "weekday_name_night_unlang": "Friday Night", 
                "ampm": "PM", 
                "tz": "", 
                "age": "", 
                "UTCDATE": ""
            }, 
            "temp": {
                "english": "41", 
                "metric": "5"
            }, 
            "dewpoint": {
                "english": "38", 
                "metric": "3"
            }, 
            "condition": "Mostly Cloudy", 
            "icon": "mostlycloudy", 
            "icon_url": "http://icons.wxug.com/i/c/k/nt_mostlycloudy.gif", 
            "fctcode": "3", 
            "sky": "71", 
            "wspd": {
                "english": "5", 
                "metric": "8"
            }, 
            "wdir": {
                "dir": "SSE", 
                "degrees": "166"
            }, 
            "wx": "Mostly Cloudy", 
            "uvi": "0", 
            "humidity": "89", 
            "windchill": {
                "english": "38", 
                "metric": "3"
            }, 
            "heatindex": {
                "english": "-9999", 
                "metric": "-9999"
            }, 
            "feelslike": {
                "english": "38", 
                "metric": "3"
            }, 
            "qpf": {
                "english": "0.0", 
                "metric": "0"
            }, 
            "snow": {
                "english": "0.0", 
                "metric": "0"
            }, 
            "pop": "24", 
            "mslp": {
                "english": "29.41", 
                "metric": "996"
            }
        }, 
        {
            "FCTTIME": {
                "hour": "22", 
                "hour_padded": "22", 
                "min": "00", 
                "min_unpadded": "0", 
                "sec": "0", 
                "year": "2017", 
                "mon": "11", 
                "mon_padded": "11", 
                "mon_abbrev": "Nov", 
                "mday": "10", 
                "mday_padded": "10", 
                "yday": "313", 
                "isdst": "0", 
                "epoch": "1510344000", 
                "pretty": "10:00 PM EET on November 10, 2017", 
                "civil": "10:00 PM", 
                "month_name": "November", 
                "month_name_abbrev": "Nov", 
                "weekday_name": "Friday", 
                "weekday_name_night": "Friday Night", 
                "weekday_name_abbrev": "Fri", 
                "weekday_name_unlang": "Friday", 
                "weekday_name_night_unlang": "Friday Night", 
                "ampm": "PM", 
                "tz": "", 
                "age": "", 
                "UTCDATE": ""
            }, 
            "temp": {
                "english": "41", 
                "metric": "5"
            }, 
            "dewpoint": {
                "english": "38", 
                "metric": "3"
            }, 
            "condition": "Chance of Rain", 
            "icon": "chancerain", 
            "icon_url": "http://icons.wxug.com/i/c/k/nt_chancerain.gif", 
            "fctcode": "12", 
            "sky": "92", 
            "wspd": {
                "english": "5", 
                "metric": "8"
            }, 
            "wdir": {
                "dir": "SSE", 
                "degrees": "158"
            }, 
            "wx": "Light Rain", 
            "uvi": "0", 
            "humidity": "90", 
            "windchill": {
                "english": "38", 
                "metric": "3"
            }, 
            "heatindex": {
                "english": "-9999", 
                "metric": "-9999"
            }, 
            "feelslike": {
                "english": "38", 
                "metric": "3"
            }, 
            "qpf": {
                "english": "0.0", 
                "metric": "0"
            }, 
            "snow": {
                "english": "0.0", 
                "metric": "0"
            }, 
            "pop": "35", 
            "mslp": {
                "english": "29.39", 
                "metric": "995"
            }
        }, 
        {
            "FCTTIME": {
                "hour": "23", 
                "hour_padded": "23", 
                "min": "00", 
                "min_unpadded": "0", 
                "sec": "0", 
                "year": "2017", 
                "mon": "11", 
                "mon_padded": "11", 
                "mon_abbrev": "Nov", 
                "mday": "10", 
                "mday_padded": "10", 
                "yday": "313", 
                "isdst": "0", 
                "epoch": "1510347600", 
                "pretty": "11:00 PM EET on November 10, 2017", 
                "civil": "11:00 PM", 
                "month_name": "November", 
                "month_name_abbrev": "Nov", 
                "weekday_name": "Friday", 
                "weekday_name_night": "Friday Night", 
                "weekday_name_abbrev": "Fri", 
                "weekday_name_unlang": "Friday", 
                "weekday_name_night_unlang": "Friday Night", 
                "ampm": "PM", 
                "tz": "", 
                "age": "", 
                "UTCDATE": ""
            }, 
            "temp": {
                "english": "40", 
                "metric": "4"
            }, 
            "dewpoint": {
                "english": "38", 
                "metric": "3"
            }, 
            "condition": "Chance of Rain", 
            "icon": "chancerain", 
            "icon_url": "http://icons.wxug.com/i/c/k/nt_chancerain.gif", 
            "fctcode": "12", 
            "sky": "91", 
            "wspd": {
                "english": "6", 
                "metric": "10"
            }, 
            "wdir": {
                "dir": "SSE", 
                "degrees": "149"
            }, 
            "wx": "Light Rain", 
            "uvi": "0", 
            "humidity": "95", 
            "windchill": {
                "english": "35", 
                "metric": "2"
            }, 
            "heatindex": {
                "english": "-9999", 
                "metric": "-9999"
            }, 
            "feelslike": {
                "english": "35", 
                "metric": "2"
            }, 
            "qpf": {
                "english": "0.01", 
                "metric": "0"
            }, 
            "snow": {
                "english": "0.0", 
                "metric": "0"
            }, 
            "pop": "40", 
            "mslp": {
                "english": "29.37", 
                "metric": "995"
            }
        }, 
        {
            "FCTTIME": {
                "hour": "0", 
                "hour_padded": "00", 
                "min": "00", 
                "min_unpadded": "0", 
                "sec": "0", 
                "year": "2017", 
                "mon": "11", 
                "mon_padded": "11", 
                "mon_abbrev": "Nov", 
                "mday": "11", 
                "mday_padded": "11", 
                "yday": "314", 
                "isdst": "0", 
                "epoch": "1510351200", 
                "pretty": "12:00 AM EET on November 11, 2017", 
                "civil": "12:00 AM", 
                "month_name": "November", 
                "month_name_abbrev": "Nov", 
                "weekday_name": "Saturday", 
                "weekday_name_night": "Saturday Night", 
                "weekday_name_abbrev": "Sat", 
                "weekday_name_unlang": "Saturday", 
                "weekday_name_night_unlang": "Saturday Night", 
                "ampm": "AM", 
                "tz": "", 
                "age": "", 
                "UTCDATE": ""
            }, 
            "temp": {
                "english": "40", 
                "metric": "4"
            }, 
            "dewpoint": {
                "english": "38", 
                "metric": "3"
            }, 
            "condition": "Chance of Rain", 
            "icon": "chancerain", 
            "icon_url": "http://icons.wxug.com/i/c/k/nt_chancerain.gif", 
            "fctcode": "12", 
            "sky": "94", 
            "wspd": {
                "english": "7", 
                "metric": "11"
            }, 
            "wdir": {
                "dir": "SE", 
                "degrees": "138"
            }, 
            "wx": "Light Rain", 
            "uvi": "0", 
            "humidity": "94", 
            "windchill": {
                "english": "34", 
                "metric": "1"
            }, 
            "heatindex": {
                "english": "-9999", 
                "metric": "-9999"
            }, 
            "feelslike": {
                "english": "34", 
                "metric": "1"
            }, 
            "qpf": {
                "english": "0.01", 
                "metric": "0"
            }, 
            "snow": {
                "english": "0.0", 
                "metric": "0"
            }, 
            "pop": "44", 
            "mslp": {
                "english": "29.35", 
                "metric": "994"
            }
        }, 
        {
            "FCTTIME": {
                "hour": "1", 
                "hour_padded": "01", 
                "min": "00", 
                "min_unpadded": "0", 
                "sec": "0", 
                "year": "2017", 
                "mon": "11", 
                "mon_padded": "11", 
                "mon_abbrev": "Nov", 
                "mday": "11", 
                "mday_padded": "11", 
                "yday": "314", 
                "isdst": "0", 
                "epoch": "1510354800", 
                "pretty": "1:00 AM EET on November 11, 2017", 
                "civil": "1:00 AM", 
                "month_name": "November", 
                "month_name_abbrev": "Nov", 
                "weekday_name": "Saturday", 
                "weekday_name_night": "Saturday Night", 
                "weekday_name_abbrev": "Sat", 
                "weekday_name_unlang": "Saturday", 
                "weekday_name_night_unlang": "Saturday Night", 
                "ampm": "AM", 
                "tz": "", 
                "age": "", 
                "UTCDATE": ""
            }, 
            "temp": {
                "english": "40", 
                "metric": "4"
            }, 
            "dewpoint": {
                "english": "38", 
                "metric": "3"
            }, 
            "condition": "Chance of Rain", 
            "icon": "chancerain", 
            "icon_url": "http://icons.wxug.com/i/c/k/nt_chancerain.gif", 
            "fctcode": "12", 
            "sky": "96", 
            "wspd": {
                "english": "7", 
                "metric": "11"
            }, 
            "wdir": {
                "dir": "SE", 
                "degrees": "129"
            }, 
            "wx": "Light Rain", 
            "uvi": "0", 
            "humidity": "93", 
            "windchill": {
                "english": "34", 
                "metric": "1"
            }, 
            "heatindex": {
                "english": "-9999", 
                "metric": "-9999"
            }, 
            "feelslike": {
                "english": "34", 
                "metric": "1"
            }, 
            "qpf": {
                "english": "0.01", 
                "metric": "0"
            }, 
            "snow": {
                "english": "0.0", 
                "metric": "0"
            }, 
            "pop": "57", 
            "mslp": {
                "english": "29.34", 
                "metric": "994"
            }
        }, 
        {
            "FCTTIME": {
                "hour": "2", 
                "hour_padded": "02", 
                "min": "00", 
                "min_unpadded": "0", 
                "sec": "0", 
                "year": "2017", 
                "mon": "11", 
                "mon_padded": "11", 
                "mon_abbrev": "Nov", 
                "mday": "11", 
                "mday_padded": "11", 
                "yday": "314", 
                "isdst": "0", 
                "epoch": "1510358400", 
                "pretty": "2:00 AM EET on November 11, 2017", 
                "civil": "2:00 AM", 
                "month_name": "November", 
                "month_name_abbrev": "Nov", 
                "weekday_name": "Saturday", 
                "weekday_name_night": "Saturday Night", 
                "weekday_name_abbrev": "Sat", 
                "weekday_name_unlang": "Saturday", 
                "weekday_name_night_unlang": "Saturday Night", 
                "ampm": "AM", 
                "tz": "", 
                "age": "", 
                "UTCDATE": ""
            }, 
            "temp": {
                "english": "40", 
                "metric": "4"
            }, 
            "dewpoint": {
                "english": "39", 
                "metric": "4"
            }, 
            "condition": "Chance of Rain", 
            "icon": "chancerain", 
            "icon_url": "http://icons.wxug.com/i/c/k/nt_chancerain.gif", 
            "fctcode": "12", 
            "sky": "96", 
            "wspd": {
                "english": "7", 
                "metric": "11"
            }, 
            "wdir": {
                "dir": "SE", 
                "degrees": "130"
            }, 
            "wx": "Light Rain", 
            "uvi": "0", 
            "humidity": "95", 
            "windchill": {
                "english": "34", 
                "metric": "1"
            }, 
            "heatindex": {
                "english": "-9999", 
                "metric": "-9999"
            }, 
            "feelslike": {
                "english": "34", 
                "metric": "1"
            }, 
            "qpf": {
                "english": "0.0", 
                "metric": "0"
            }, 
            "snow": {
                "english": "0.0", 
                "metric": "0"
            }, 
            "pop": "39", 
            "mslp": {
                "english": "29.31", 
                "metric": "993"
            }
        }, 
        {
            "FCTTIME": {
                "hour": "3", 
                "hour_padded": "03", 
                "min": "00", 
                "min_unpadded": "0", 
                "sec": "0", 
                "year": "2017", 
                "mon": "11", 
                "mon_padded": "11", 
                "mon_abbrev": "Nov", 
                "mday": "11", 
                "mday_padded": "11", 
                "yday": "314", 
                "isdst": "0", 
                "epoch": "1510362000", 
                "pretty": "3:00 AM EET on November 11, 2017", 
                "civil": "3:00 AM", 
                "month_name": "November", 
                "month_name_abbrev": "Nov", 
                "weekday_name": "Saturday", 
                "weekday_name_night": "Saturday Night", 
                "weekday_name_abbrev": "Sat", 
                "weekday_name_unlang": "Saturday", 
                "weekday_name_night_unlang": "Saturday Night", 
                "ampm": "AM", 
                "tz": "", 
                "age": "", 
                "UTCDATE": ""
            }, 
            "temp": {
                "english": "41", 
                "metric": "5"
            }, 
            "dewpoint": {
                "english": "39", 
                "metric": "4"
            }, 
            "condition": "Chance of Rain", 
            "icon": "chancerain", 
            "icon_url": "http://icons.wxug.com/i/c/k/nt_chancerain.gif", 
            "fctcode": "12", 
            "sky": "98", 
            "wspd": {
                "english": "8", 
                "metric": "13"
            }, 
            "wdir": {
                "dir": "SE", 
                "degrees": "131"
            }, 
            "wx": "Light Rain", 
            "uvi": "0", 
            "humidity": "93", 
            "windchill": {
                "english": "36", 
                "metric": "2"
            }, 
            "heatindex": {
                "english": "-9999", 
                "metric": "-9999"
            }, 
            "feelslike": {
                "english": "36", 
                "metric": "2"
            }, 
            "qpf": {
                "english": "0.02", 
                "metric": "1"
            }, 
            "snow": {
                "english": "0.0", 
                "metric": "0"
            }, 
            "pop": "72", 
            "mslp": {
                "english": "29.28", 
                "metric": "992"
            }
        }, 
        {
            "FCTTIME": {
                "hour": "4", 
                "hour_padded": "04", 
                "min": "00", 
                "min_unpadded": "0", 
                "sec": "0", 
                "year": "2017", 
                "mon": "11", 
                "mon_padded": "11", 
                "mon_abbrev": "Nov", 
                "mday": "11", 
                "mday_padded": "11", 
                "yday": "314", 
                "isdst": "0", 
                "epoch": "1510365600", 
                "pretty": "4:00 AM EET on November 11, 2017", 
                "civil": "4:00 AM", 
                "month_name": "November", 
                "month_name_abbrev": "Nov", 
                "weekday_name": "Saturday", 
                "weekday_name_night": "Saturday Night", 
                "weekday_name_abbrev": "Sat", 
                "weekday_name_unlang": "Saturday", 
                "weekday_name_night_unlang": "Saturday Night", 
                "ampm": "AM", 
                "tz": "", 
                "age": "", 
                "UTCDATE": ""
            }, 
            "temp": {
                "english": "40", 
                "metric": "4"
            }, 
            "dewpoint": {
                "english": "39", 
                "metric": "4"
            }, 
            "condition": "Chance of Rain", 
            "icon": "chancerain", 
            "icon_url": "http://icons.wxug.com/i/c/k/nt_chancerain.gif", 
            "fctcode": "12", 
            "sky": "99", 
            "wspd": {
                "english": "9", 
                "metric": "14"
            }, 
            "wdir": {
                "dir": "SE", 
                "degrees": "126"
            }, 
            "wx": "Light Rain", 
            "uvi": "0", 
            "humidity": "95", 
            "windchill": {
                "english": "33", 
                "metric": "1"
            }, 
            "heatindex": {
                "english": "-9999", 
                "metric": "-9999"
            }, 
            "feelslike": {
                "english": "33", 
                "metric": "1"
            }, 
            "qpf": {
                "english": "0.02", 
                "metric": "1"
            }, 
            "snow": {
                "english": "0.0", 
                "metric": "0"
            }, 
            "pop": "74", 
            "mslp": {
                "english": "29.25", 
                "metric": "991"
            }
        }, 
        {
            "FCTTIME": {
                "hour": "5", 
                "hour_padded": "05", 
                "min": "00", 
                "min_unpadded": "0", 
                "sec": "0", 
                "year": "2017", 
                "mon": "11", 
                "mon_padded": "11", 
                "mon_abbrev": "Nov", 
                "mday": "11", 
                "mday_padded": "11", 
                "yday": "314", 
                "isdst": "0", 
                "epoch": "1510369200", 
                "pretty": "5:00 AM EET on November 11, 2017", 
                "civil": "5:00 AM", 
                "month_name": "November", 
                "month_name_abbrev": "Nov", 
                "weekday_name": "Saturday", 
                "weekday_name_night": "Saturday Night", 
                "weekday_name_abbrev": "Sat", 
                "weekday_name_unlang": "Saturday", 
                "weekday_name_night_unlang": "Saturday Night", 
                "ampm": "AM", 
                "tz": "", 
                "age": "", 
                "UTCDATE": ""
            }, 
            "temp": {
                "english": "40", 
                "metric": "4"
            }, 
            "dewpoint": {
                "english": "38", 
                "metric": "3"
            }, 
            "condition": "Chance of Rain", 
            "icon": "chancerain", 
            "icon_url": "http://icons.wxug.com/i/c/k/nt_chancerain.gif", 
            "fctcode": "12", 
            "sky": "100", 
            "wspd": {
                "english": "10", 
                "metric": "16"
            }, 
            "wdir": {
                "dir": "SE", 
                "degrees": "124"
            }, 
            "wx": "Light Rain", 
            "uvi": "0", 
            "humidity": "94", 
            "windchill": {
                "english": "33", 
                "metric": "0"
            }, 
            "heatindex": {
                "english": "-9999", 
                "metric": "-9999"
            }, 
            "feelslike": {
                "english": "33", 
                "metric": "0"
            }, 
            "qpf": {
                "english": "0.01", 
                "metric": "0"
            }, 
            "snow": {
                "english": "0.0", 
                "metric": "0"
            }, 
            "pop": "54", 
            "mslp": {
                "english": "29.22", 
                "metric": "990"
            }
        }, 
        {
            "FCTTIME": {
                "hour": "6", 
                "hour_padded": "06", 
                "min": "00", 
                "min_unpadded": "0", 
                "sec": "0", 
                "year": "2017", 
                "mon": "11", 
                "mon_padded": "11", 
                "mon_abbrev": "Nov", 
                "mday": "11", 
                "mday_padded": "11", 
                "yday": "314", 
                "isdst": "0", 
                "epoch": "1510372800", 
                "pretty": "6:00 AM EET on November 11, 2017", 
                "civil": "6:00 AM", 
                "month_name": "November", 
                "month_name_abbrev": "Nov", 
                "weekday_name": "Saturday", 
                "weekday_name_night": "Saturday Night", 
                "weekday_name_abbrev": "Sat", 
                "weekday_name_unlang": "Saturday", 
                "weekday_name_night_unlang": "Saturday Night", 
                "ampm": "AM", 
                "tz": "", 
                "age": "", 
                "UTCDATE": ""
            }, 
            "temp": {
                "english": "40", 
                "metric": "4"
            }, 
            "dewpoint": {
                "english": "39", 
                "metric": "4"
            }, 
            "condition": "Chance of Rain", 
            "icon": "chancerain", 
            "icon_url": "http://icons.wxug.com/i/c/k/nt_chancerain.gif", 
            "fctcode": "12", 
            "sky": "100", 
            "wspd": {
                "english": "11", 
                "metric": "18"
            }, 
            "wdir": {
                "dir": "SE", 
                "degrees": "126"
            }, 
            "wx": "Light Rain", 
            "uvi": "0", 
            "humidity": "96", 
            "windchill": {
                "english": "32", 
                "metric": "0"
            }, 
            "heatindex": {
                "english": "-9999", 
                "metric": "-9999"
            }, 
            "feelslike": {
                "english": "32", 
                "metric": "0"
            }, 
            "qpf": {
                "english": "0.01", 
                "metric": "0"
            }, 
            "snow": {
                "english": "0.0", 
                "metric": "0"
            }, 
            "pop": "48", 
            "mslp": {
                "english": "29.19", 
                "metric": "988"
            }
        }, 
        {
            "FCTTIME": {
                "hour": "7", 
                "hour_padded": "07", 
                "min": "00", 
                "min_unpadded": "0", 
                "sec": "0", 
                "year": "2017", 
                "mon": "11", 
                "mon_padded": "11", 
                "mon_abbrev": "Nov", 
                "mday": "11", 
                "mday_padded": "11", 
                "yday": "314", 
                "isdst": "0", 
                "epoch": "1510376400", 
                "pretty": "7:00 AM EET on November 11, 2017", 
                "civil": "7:00 AM", 
                "month_name": "November", 
                "month_name_abbrev": "Nov", 
                "weekday_name": "Saturday", 
                "weekday_name_night": "Saturday Night", 
                "weekday_name_abbrev": "Sat", 
                "weekday_name_unlang": "Saturday", 
                "weekday_name_night_unlang": "Saturday Night", 
                "ampm": "AM", 
                "tz": "", 
                "age": "", 
                "UTCDATE": ""
            }, 
            "temp": {
                "english": "40", 
                "metric": "4"
            }, 
            "dewpoint": {
                "english": "39", 
                "metric": "4"
            }, 
            "condition": "Chance of Rain", 
            "icon": "chancerain", 
            "icon_url": "http://icons.wxug.com/i/c/k/nt_chancerain.gif", 
            "fctcode": "12", 
            "sky": "100", 
            "wspd": {
                "english": "11", 
                "metric": "18"
            }, 
            "wdir": {
                "dir": "ESE", 
                "degrees": "118"
            }, 
            "wx": "Light Rain", 
            "uvi": "0", 
            "humidity": "98", 
            "windchill": {
                "english": "32", 
                "metric": "0"
            }, 
            "heatindex": {
                "english": "-9999", 
                "metric": "-9999"
            }, 
            "feelslike": {
                "english": "32", 
                "metric": "0"
            }, 
            "qpf": {
                "english": "0.01", 
                "metric": "0"
            }, 
            "snow": {
                "english": "0.0", 
                "metric": "0"
            }, 
            "pop": "67", 
            "mslp": {
                "english": "29.17", 
                "metric": "988"
            }
        }, 
        {
            "FCTTIME": {
                "hour": "8", 
                "hour_padded": "08", 
                "min": "00", 
                "min_unpadded": "0", 
                "sec": "0", 
                "year": "2017", 
                "mon": "11", 
                "mon_padded": "11", 
                "mon_abbrev": "Nov", 
                "mday": "11", 
                "mday_padded": "11", 
                "yday": "314", 
                "isdst": "0", 
                "epoch": "1510380000", 
                "pretty": "8:00 AM EET on November 11, 2017", 
                "civil": "8:00 AM", 
                "month_name": "November", 
                "month_name_abbrev": "Nov", 
                "weekday_name": "Saturday", 
                "weekday_name_night": "Saturday Night", 
                "weekday_name_abbrev": "Sat", 
                "weekday_name_unlang": "Saturday", 
                "weekday_name_night_unlang": "Saturday Night", 
                "ampm": "AM", 
                "tz": "", 
                "age": "", 
                "UTCDATE": ""
            }, 
            "temp": {
                "english": "39", 
                "metric": "4"
            }, 
            "dewpoint": {
                "english": "39", 
                "metric": "4"
            }, 
            "condition": "Chance of Rain", 
            "icon": "chancerain", 
            "icon_url": "http://icons.wxug.com/i/c/k/nt_chancerain.gif", 
            "fctcode": "12", 
            "sky": "100", 
            "wspd": {
                "english": "11", 
                "metric": "18"
            }, 
            "wdir": {
                "dir": "ESE", 
                "degrees": "116"
            }, 
            "wx": "Light Rain", 
            "uvi": "0", 
            "humidity": "99", 
            "windchill": {
                "english": "32", 
                "metric": "0"
            }, 
            "heatindex": {
                "english": "-9999", 
                "metric": "-9999"
            }, 
            "feelslike": {
                "english": "32", 
                "metric": "0"
            }, 
            "qpf": {
                "english": "0.02", 
                "metric": "1"
            }, 
            "snow": {
                "english": "0.0", 
                "metric": "0"
            }, 
            "pop": "70", 
            "mslp": {
                "english": "29.14", 
                "metric": "987"
            }
        }, 
        {
            "FCTTIME": {
                "hour": "9", 
                "hour_padded": "09", 
                "min": "00", 
                "min_unpadded": "0", 
                "sec": "0", 
                "year": "2017", 
                "mon": "11", 
                "mon_padded": "11", 
                "mon_abbrev": "Nov", 
                "mday": "11", 
                "mday_padded": "11", 
                "yday": "314", 
                "isdst": "0", 
                "epoch": "1510383600", 
                "pretty": "9:00 AM EET on November 11, 2017", 
                "civil": "9:00 AM", 
                "month_name": "November", 
                "month_name_abbrev": "Nov", 
                "weekday_name": "Saturday", 
                "weekday_name_night": "Saturday Night", 
                "weekday_name_abbrev": "Sat", 
                "weekday_name_unlang": "Saturday", 
                "weekday_name_night_unlang": "Saturday Night", 
                "ampm": "AM", 
                "tz": "", 
                "age": "", 
                "UTCDATE": ""
            }, 
            "temp": {
                "english": "39", 
                "metric": "4"
            }, 
            "dewpoint": {
                "english": "39", 
                "metric": "4"
            }, 
            "condition": "Chance of Rain", 
            "icon": "chancerain", 
            "icon_url": "http://icons.wxug.com/i/c/k/chancerain.gif", 
            "fctcode": "12", 
            "sky": "100", 
            "wspd": {
                "english": "10", 
                "metric": "16"
            }, 
            "wdir": {
                "dir": "ESE", 
                "degrees": "115"
            }, 
            "wx": "Light Rain", 
            "uvi": "0", 
            "humidity": "97", 
            "windchill": {
                "english": "33", 
                "metric": "0"
            }, 
            "heatindex": {
                "english": "-9999", 
                "metric": "-9999"
            }, 
            "feelslike": {
                "english": "33", 
                "metric": "0"
            }, 
            "qpf": {
                "english": "0.01", 
                "metric": "0"
            }, 
            "snow": {
                "english": "0.0", 
                "metric": "0"
            }, 
            "pop": "60", 
            "mslp": {
                "english": "29.12", 
                "metric": "986"
            }
        }, 
        {
            "FCTTIME": {
                "hour": "10", 
                "hour_padded": "10", 
                "min": "00", 
                "min_unpadded": "0", 
                "sec": "0", 
                "year": "2017", 
                "mon": "11", 
                "mon_padded": "11", 
                "mon_abbrev": "Nov", 
                "mday": "11", 
                "mday_padded": "11", 
                "yday": "314", 
                "isdst": "0", 
                "epoch": "1510387200", 
                "pretty": "10:00 AM EET on November 11, 2017", 
                "civil": "10:00 AM", 
                "month_name": "November", 
                "month_name_abbrev": "Nov", 
                "weekday_name": "Saturday", 
                "weekday_name_night": "Saturday Night", 
                "weekday_name_abbrev": "Sat", 
                "weekday_name_unlang": "Saturday", 
                "weekday_name_night_unlang": "Saturday Night", 
                "ampm": "AM", 
                "tz": "", 
                "age": "", 
                "UTCDATE": ""
            }, 
            "temp": {
                "english": "39", 
                "metric": "4"
            }, 
            "dewpoint": {
                "english": "39", 
                "metric": "4"
            }, 
            "condition": "Chance of Rain", 
            "icon": "chancerain", 
            "icon_url": "http://icons.wxug.com/i/c/k/chancerain.gif", 
            "fctcode": "12", 
            "sky": "100", 
            "wspd": {
                "english": "10", 
                "metric": "16"
            }, 
            "wdir": {
                "dir": "ESE", 
                "degrees": "112"
            }, 
            "wx": "Light Rain", 
            "uvi": "0", 
            "humidity": "100", 
            "windchill": {
                "english": "33", 
                "metric": "0"
            }, 
            "heatindex": {
                "english": "-9999", 
                "metric": "-9999"
            }, 
            "feelslike": {
                "english": "33", 
                "metric": "0"
            }, 
            "qpf": {
                "english": "0.02", 
                "metric": "1"
            }, 
            "snow": {
                "english": "0.0", 
                "metric": "0"
            }, 
            "pop": "69", 
            "mslp": {
                "english": "29.09", 
                "metric": "985"
            }
        }, 
        {
            "FCTTIME": {
                "hour": "11", 
                "hour_padded": "11", 
                "min": "00", 
                "min_unpadded": "0", 
                "sec": "0", 
                "year": "2017", 
                "mon": "11", 
                "mon_padded": "11", 
                "mon_abbrev": "Nov", 
                "mday": "11", 
                "mday_padded": "11", 
                "yday": "314", 
                "isdst": "0", 
                "epoch": "1510390800", 
                "pretty": "11:00 AM EET on November 11, 2017", 
                "civil": "11:00 AM", 
                "month_name": "November", 
                "month_name_abbrev": "Nov", 
                "weekday_name": "Saturday", 
                "weekday_name_night": "Saturday Night", 
                "weekday_name_abbrev": "Sat", 
                "weekday_name_unlang": "Saturday", 
                "weekday_name_night_unlang": "Saturday Night", 
                "ampm": "AM", 
                "tz": "", 
                "age": "", 
                "UTCDATE": ""
            }, 
            "temp": {
                "english": "40", 
                "metric": "4"
            }, 
            "dewpoint": {
                "english": "39", 
                "metric": "4"
            }, 
            "condition": "Rain", 
            "icon": "rain", 
            "icon_url": "http://icons.wxug.com/i/c/k/rain.gif", 
            "fctcode": "13", 
            "sky": "100", 
            "wspd": {
                "english": "10", 
                "metric": "16"
            }, 
            "wdir": {
                "dir": "ESE", 
                "degrees": "111"
            }, 
            "wx": "Rain", 
            "uvi": "0", 
            "humidity": "99", 
            "windchill": {
                "english": "33", 
                "metric": "0"
            }, 
            "heatindex": {
                "english": "-9999", 
                "metric": "-9999"
            }, 
            "feelslike": {
                "english": "33", 
                "metric": "0"
            }, 
            "qpf": {
                "english": "0.03", 
                "metric": "1"
            }, 
            "snow": {
                "english": "0.0", 
                "metric": "0"
            }, 
            "pop": "85", 
            "mslp": {
                "english": "29.07", 
                "metric": "984"
            }
        }, 
        {
            "FCTTIME": {
                "hour": "12", 
                "hour_padded": "12", 
                "min": "00", 
                "min_unpadded": "0", 
                "sec": "0", 
                "year": "2017", 
                "mon": "11", 
                "mon_padded": "11", 
                "mon_abbrev": "Nov", 
                "mday": "11", 
                "mday_padded": "11", 
                "yday": "314", 
                "isdst": "0", 
                "epoch": "1510394400", 
                "pretty": "12:00 PM EET on November 11, 2017", 
                "civil": "12:00 PM", 
                "month_name": "November", 
                "month_name_abbrev": "Nov", 
                "weekday_name": "Saturday", 
                "weekday_name_night": "Saturday Night", 
                "weekday_name_abbrev": "Sat", 
                "weekday_name_unlang": "Saturday", 
                "weekday_name_night_unlang": "Saturday Night", 
                "ampm": "PM", 
                "tz": "", 
                "age": "", 
                "UTCDATE": ""
            }, 
            "temp": {
                "english": "40", 
                "metric": "4"
            }, 
            "dewpoint": {
                "english": "39", 
                "metric": "4"
            }, 
            "condition": "Rain", 
            "icon": "rain", 
            "icon_url": "http://icons.wxug.com/i/c/k/rain.gif", 
            "fctcode": "13", 
            "sky": "100", 
            "wspd": {
                "english": "9", 
                "metric": "14"
            }, 
            "wdir": {
                "dir": "ESE", 
                "degrees": "116"
            }, 
            "wx": "Rain", 
            "uvi": "0", 
            "humidity": "98", 
            "windchill": {
                "english": "33", 
                "metric": "1"
            }, 
            "heatindex": {
                "english": "-9999", 
                "metric": "-9999"
            }, 
            "feelslike": {
                "english": "33", 
                "metric": "1"
            }, 
            "qpf": {
                "english": "0.03", 
                "metric": "1"
            }, 
            "snow": {
                "english": "0.0", 
                "metric": "0"
            }, 
            "pop": "85", 
            "mslp": {
                "english": "29.05", 
                "metric": "984"
            }
        }, 
        {
            "FCTTIME": {
                "hour": "13", 
                "hour_padded": "13", 
                "min": "00", 
                "min_unpadded": "0", 
                "sec": "0", 
                "year": "2017", 
                "mon": "11", 
                "mon_padded": "11", 
                "mon_abbrev": "Nov", 
                "mday": "11", 
                "mday_padded": "11", 
                "yday": "314", 
                "isdst": "0", 
                "epoch": "1510398000", 
                "pretty": "1:00 PM EET on November 11, 2017", 
                "civil": "1:00 PM", 
                "month_name": "November", 
                "month_name_abbrev": "Nov", 
                "weekday_name": "Saturday", 
                "weekday_name_night": "Saturday Night", 
                "weekday_name_abbrev": "Sat", 
                "weekday_name_unlang": "Saturday", 
                "weekday_name_night_unlang": "Saturday Night", 
                "ampm": "PM", 
                "tz": "", 
                "age": "", 
                "UTCDATE": ""
            }, 
            "temp": {
                "english": "40", 
                "metric": "4"
            }, 
            "dewpoint": {
                "english": "39", 
                "metric": "4"
            }, 
            "condition": "Chance of Rain", 
            "icon": "chancerain", 
            "icon_url": "http://icons.wxug.com/i/c/k/chancerain.gif", 
            "fctcode": "12", 
            "sky": "100", 
            "wspd": {
                "english": "9", 
                "metric": "14"
            }, 
            "wdir": {
                "dir": "SE", 
                "degrees": "125"
            }, 
            "wx": "Light Rain", 
            "uvi": "0", 
            "humidity": "97", 
            "windchill": {
                "english": "33", 
                "metric": "1"
            }, 
            "heatindex": {
                "english": "-9999", 
                "metric": "-9999"
            }, 
            "feelslike": {
                "english": "33", 
                "metric": "1"
            }, 
            "qpf": {
                "english": "0.02", 
                "metric": "1"
            }, 
            "snow": {
                "english": "0.0", 
                "metric": "0"
            }, 
            "pop": "71", 
            "mslp": {
                "english": "29.02", 
                "metric": "983"
            }
        }, 
        {
            "FCTTIME": {
                "hour": "14", 
                "hour_padded": "14", 
                "min": "00", 
                "min_unpadded": "0", 
                "sec": "0", 
                "year": "2017", 
                "mon": "11", 
                "mon_padded": "11", 
                "mon_abbrev": "Nov", 
                "mday": "11", 
                "mday_padded": "11", 
                "yday": "314", 
                "isdst": "0", 
                "epoch": "1510401600", 
                "pretty": "2:00 PM EET on November 11, 2017", 
                "civil": "2:00 PM", 
                "month_name": "November", 
                "month_name_abbrev": "Nov", 
                "weekday_name": "Saturday", 
                "weekday_name_night": "Saturday Night", 
                "weekday_name_abbrev": "Sat", 
                "weekday_name_unlang": "Saturday", 
                "weekday_name_night_unlang": "Saturday Night", 
                "ampm": "PM", 
                "tz": "", 
                "age": "", 
                "UTCDATE": ""
            }, 
            "temp": {
                "english": "40", 
                "metric": "4"
            }, 
            "dewpoint": {
                "english": "39", 
                "metric": "4"
            }, 
            "condition": "Chance of Rain", 
            "icon": "chancerain", 
            "icon_url": "http://icons.wxug.com/i/c/k/chancerain.gif", 
            "fctcode": "12", 
            "sky": "100", 
            "wspd": {
                "english": "9", 
                "metric": "14"
            }, 
            "wdir": {
                "dir": "SE", 
                "degrees": "128"
            }, 
            "wx": "Light Rain", 
            "uvi": "0", 
            "humidity": "93", 
            "windchill": {
                "english": "33", 
                "metric": "1"
            }, 
            "heatindex": {
                "english": "-9999", 
                "metric": "-9999"
            }, 
            "feelslike": {
                "english": "33", 
                "metric": "1"
            }, 
            "qpf": {
                "english": "0.02", 
                "metric": "1"
            }, 
            "snow": {
                "english": "0.0", 
                "metric": "0"
            }, 
            "pop": "64", 
            "mslp": {
                "english": "29.01", 
                "metric": "982"
            }
        }, 
        {
            "FCTTIME": {
                "hour": "15", 
                "hour_padded": "15", 
                "min": "00", 
                "min_unpadded": "0", 
                "sec": "0", 
                "year": "2017", 
                "mon": "11", 
                "mon_padded": "11", 
                "mon_abbrev": "Nov", 
                "mday": "11", 
                "mday_padded": "11", 
                "yday": "314", 
                "isdst": "0", 
                "epoch": "1510405200", 
                "pretty": "3:00 PM EET on November 11, 2017", 
                "civil": "3:00 PM", 
                "month_name": "November", 
                "month_name_abbrev": "Nov", 
                "weekday_name": "Saturday", 
                "weekday_name_night": "Saturday Night", 
                "weekday_name_abbrev": "Sat", 
                "weekday_name_unlang": "Saturday", 
                "weekday_name_night_unlang": "Saturday Night", 
                "ampm": "PM", 
                "tz": "", 
                "age": "", 
                "UTCDATE": ""
            }, 
            "temp": {
                "english": "41", 
                "metric": "5"
            }, 
            "dewpoint": {
                "english": "38", 
                "metric": "3"
            }, 
            "condition": "Chance of Rain", 
            "icon": "chancerain", 
            "icon_url": "http://icons.wxug.com/i/c/k/chancerain.gif", 
            "fctcode": "12", 
            "sky": "97", 
            "wspd": {
                "english": "8", 
                "metric": "13"
            }, 
            "wdir": {
                "dir": "SE", 
                "degrees": "125"
            }, 
            "wx": "Light Rain", 
            "uvi": "0", 
            "humidity": "90", 
            "windchill": {
                "english": "36", 
                "metric": "2"
            }, 
            "heatindex": {
                "english": "-9999", 
                "metric": "-9999"
            }, 
            "feelslike": {
                "english": "36", 
                "metric": "2"
            }, 
            "qpf": {
                "english": "0.02", 
                "metric": "1"
            }, 
            "snow": {
                "english": "0.0", 
                "metric": "0"
            }, 
            "pop": "63", 
            "mslp": {
                "english": "28.99", 
                "metric": "982"
            }
        }, 
        {
            "FCTTIME": {
                "hour": "16", 
                "hour_padded": "16", 
                "min": "00", 
                "min_unpadded": "0", 
                "sec": "0", 
                "year": "2017", 
                "mon": "11", 
                "mon_padded": "11", 
                "mon_abbrev": "Nov", 
                "mday": "11", 
                "mday_padded": "11", 
                "yday": "314", 
                "isdst": "0", 
                "epoch": "1510408800", 
                "pretty": "4:00 PM EET on November 11, 2017", 
                "civil": "4:00 PM", 
                "month_name": "November", 
                "month_name_abbrev": "Nov", 
                "weekday_name": "Saturday", 
                "weekday_name_night": "Saturday Night", 
                "weekday_name_abbrev": "Sat", 
                "weekday_name_unlang": "Saturday", 
                "weekday_name_night_unlang": "Saturday Night", 
                "ampm": "PM", 
                "tz": "", 
                "age": "", 
                "UTCDATE": ""
            }, 
            "temp": {
                "english": "40", 
                "metric": "4"
            }, 
            "dewpoint": {
                "english": "37", 
                "metric": "3"
            }, 
            "condition": "Chance of Rain", 
            "icon": "chancerain", 
            "icon_url": "http://icons.wxug.com/i/c/k/chancerain.gif", 
            "fctcode": "12", 
            "sky": "89", 
            "wspd": {
                "english": "7", 
                "metric": "11"
            }, 
            "wdir": {
                "dir": "ESE", 
                "degrees": "123"
            }, 
            "wx": "Showers", 
            "uvi": "0", 
            "humidity": "89", 
            "windchill": {
                "english": "34", 
                "metric": "1"
            }, 
            "heatindex": {
                "english": "-9999", 
                "metric": "-9999"
            }, 
            "feelslike": {
                "english": "34", 
                "metric": "1"
            }, 
            "qpf": {
                "english": "0.01", 
                "metric": "0"
            }, 
            "snow": {
                "english": "0.0", 
                "metric": "0"
            }, 
            "pop": "57", 
            "mslp": {
                "english": "28.98", 
                "metric": "981"
            }
        }, 
        {
            "FCTTIME": {
                "hour": "17", 
                "hour_padded": "17", 
                "min": "00", 
                "min_unpadded": "0", 
                "sec": "0", 
                "year": "2017", 
                "mon": "11", 
                "mon_padded": "11", 
                "mon_abbrev": "Nov", 
                "mday": "11", 
                "mday_padded": "11", 
                "yday": "314", 
                "isdst": "0", 
                "epoch": "1510412400", 
                "pretty": "5:00 PM EET on November 11, 2017", 
                "civil": "5:00 PM", 
                "month_name": "November", 
                "month_name_abbrev": "Nov", 
                "weekday_name": "Saturday", 
                "weekday_name_night": "Saturday Night", 
                "weekday_name_abbrev": "Sat", 
                "weekday_name_unlang": "Saturday", 
                "weekday_name_night_unlang": "Saturday Night", 
                "ampm": "PM", 
                "tz": "", 
                "age": "", 
                "UTCDATE": ""
            }, 
            "temp": {
                "english": "39", 
                "metric": "4"
            }, 
            "dewpoint": {
                "english": "37", 
                "metric": "3"
            }, 
            "condition": "Chance of Rain", 
            "icon": "chancerain", 
            "icon_url": "http://icons.wxug.com/i/c/k/nt_chancerain.gif", 
            "fctcode": "12", 
            "sky": "88", 
            "wspd": {
                "english": "7", 
                "metric": "11"
            }, 
            "wdir": {
                "dir": "ESE", 
                "degrees": "119"
            }, 
            "wx": "Showers", 
            "uvi": "0", 
            "humidity": "90", 
            "windchill": {
                "english": "34", 
                "metric": "1"
            }, 
            "heatindex": {
                "english": "-9999", 
                "metric": "-9999"
            }, 
            "feelslike": {
                "english": "34", 
                "metric": "1"
            }, 
            "qpf": {
                "english": "0.0", 
                "metric": "0"
            }, 
            "snow": {
                "english": "0.0", 
                "metric": "0"
            }, 
            "pop": "38", 
            "mslp": {
                "english": "28.96", 
                "metric": "981"
            }
        }, 
        {
            "FCTTIME": {
                "hour": "18", 
                "hour_padded": "18", 
                "min": "00", 
                "min_unpadded": "0", 
                "sec": "0", 
                "year": "2017", 
                "mon": "11", 
                "mon_padded": "11", 
                "mon_abbrev": "Nov", 
                "mday": "11", 
                "mday_padded": "11", 
                "yday": "314", 
                "isdst": "0", 
                "epoch": "1510416000", 
                "pretty": "6:00 PM EET on November 11, 2017", 
                "civil": "6:00 PM", 
                "month_name": "November", 
                "month_name_abbrev": "Nov", 
                "weekday_name": "Saturday", 
                "weekday_name_night": "Saturday Night", 
                "weekday_name_abbrev": "Sat", 
                "weekday_name_unlang": "Saturday", 
                "weekday_name_night_unlang": "Saturday Night", 
                "ampm": "PM", 
                "tz": "", 
                "age": "", 
                "UTCDATE": ""
            }, 
            "temp": {
                "english": "38", 
                "metric": "3"
            }, 
            "dewpoint": {
                "english": "37", 
                "metric": "3"
            }, 
            "condition": "Chance of Rain", 
            "icon": "chancerain", 
            "icon_url": "http://icons.wxug.com/i/c/k/nt_chancerain.gif", 
            "fctcode": "12", 
            "sky": "92", 
            "wspd": {
                "english": "7", 
                "metric": "11"
            }, 
            "wdir": {
                "dir": "ESE", 
                "degrees": "121"
            }, 
            "wx": "Showers", 
            "uvi": "0", 
            "humidity": "94", 
            "windchill": {
                "english": "32", 
                "metric": "0"
            }, 
            "heatindex": {
                "english": "-9999", 
                "metric": "-9999"
            }, 
            "feelslike": {
                "english": "32", 
                "metric": "0"
            }, 
            "qpf": {
                "english": "0.0", 
                "metric": "0"
            }, 
            "snow": {
                "english": "0.0", 
                "metric": "0"
            }, 
            "pop": "35", 
            "mslp": {
                "english": "28.95", 
                "metric": "980"
            }
        }, 
        {
            "FCTTIME": {
                "hour": "19", 
                "hour_padded": "19", 
                "min": "00", 
                "min_unpadded": "0", 
                "sec": "0", 
                "year": "2017", 
                "mon": "11", 
                "mon_padded": "11", 
                "mon_abbrev": "Nov", 
                "mday": "11", 
                "mday_padded": "11", 
                "yday": "314", 
                "isdst": "0", 
                "epoch": "1510419600", 
                "pretty": "7:00 PM EET on November 11, 2017", 
                "civil": "7:00 PM", 
                "month_name": "November", 
                "month_name_abbrev": "Nov", 
                "weekday_name": "Saturday", 
                "weekday_name_night": "Saturday Night", 
                "weekday_name_abbrev": "Sat", 
                "weekday_name_unlang": "Saturday", 
                "weekday_name_night_unlang": "Saturday Night", 
                "ampm": "PM", 
                "tz": "", 
                "age": "", 
                "UTCDATE": ""
            }, 
            "temp": {
                "english": "38", 
                "metric": "3"
            }, 
            "dewpoint": {
                "english": "37", 
                "metric": "3"
            }, 
            "condition": "Chance of Rain", 
            "icon": "chancerain", 
            "icon_url": "http://icons.wxug.com/i/c/k/nt_chancerain.gif", 
            "fctcode": "12", 
            "sky": "94", 
            "wspd": {
                "english": "6", 
                "metric": "10"
            }, 
            "wdir": {
                "dir": "ESE", 
                "degrees": "119"
            }, 
            "wx": "Showers", 
            "uvi": "0", 
            "humidity": "95", 
            "windchill": {
                "english": "33", 
                "metric": "0"
            }, 
            "heatindex": {
                "english": "-9999", 
                "metric": "-9999"
            }, 
            "feelslike": {
                "english": "33", 
                "metric": "0"
            }, 
            "qpf": {
                "english": "0.0", 
                "metric": "0"
            }, 
            "snow": {
                "english": "0.0", 
                "metric": "0"
            }, 
            "pop": "35", 
            "mslp": {
                "english": "28.93", 
                "metric": "980"
            }
        }, 
        {
            "FCTTIME": {
                "hour": "20", 
                "hour_padded": "20", 
                "min": "00", 
                "min_unpadded": "0", 
                "sec": "0", 
                "year": "2017", 
                "mon": "11", 
                "mon_padded": "11", 
                "mon_abbrev": "Nov", 
                "mday": "11", 
                "mday_padded": "11", 
                "yday": "314", 
                "isdst": "0", 
                "epoch": "1510423200", 
                "pretty": "8:00 PM EET on November 11, 2017", 
                "civil": "8:00 PM", 
                "month_name": "November", 
                "month_name_abbrev": "Nov", 
                "weekday_name": "Saturday", 
                "weekday_name_night": "Saturday Night", 
                "weekday_name_abbrev": "Sat", 
                "weekday_name_unlang": "Saturday", 
                "weekday_name_night_unlang": "Saturday Night", 
                "ampm": "PM", 
                "tz": "", 
                "age": "", 
                "UTCDATE": ""
            }, 
            "temp": {
                "english": "38", 
                "metric": "3"
            }, 
            "dewpoint": {
                "english": "37", 
                "metric": "3"
            }, 
            "condition": "Chance of Rain", 
            "icon": "chancerain", 
            "icon_url": "http://icons.wxug.com/i/c/k/nt_chancerain.gif", 
            "fctcode": "12", 
            "sky": "93", 
            "wspd": {
                "english": "5", 
                "metric": "8"
            }, 
            "wdir": {
                "dir": "ESE", 
                "degrees": "119"
            }, 
            "wx": "Showers", 
            "uvi": "0", 
            "humidity": "95", 
            "windchill": {
                "english": "33", 
                "metric": "1"
            }, 
            "heatindex": {
                "english": "-9999", 
                "metric": "-9999"
            }, 
            "feelslike": {
                "english": "33", 
                "metric": "1"
            }, 
            "qpf": {
                "english": "0.01", 
                "metric": "0"
            }, 
            "snow": {
                "english": "0.0", 
                "metric": "0"
            }, 
            "pop": "38", 
            "mslp": {
                "english": "28.93", 
                "metric": "980"
            }
        }, 
        {
            "FCTTIME": {
                "hour": "21", 
                "hour_padded": "21", 
                "min": "00", 
                "min_unpadded": "0", 
                "sec": "0", 
                "year": "2017", 
                "mon": "11", 
                "mon_padded": "11", 
                "mon_abbrev": "Nov", 
                "mday": "11", 
                "mday_padded": "11", 
                "yday": "314", 
                "isdst": "0", 
                "epoch": "1510426800", 
                "pretty": "9:00 PM EET on November 11, 2017", 
                "civil": "9:00 PM", 
                "month_name": "November", 
                "month_name_abbrev": "Nov", 
                "weekday_name": "Saturday", 
                "weekday_name_night": "Saturday Night", 
                "weekday_name_abbrev": "Sat", 
                "weekday_name_unlang": "Saturday", 
                "weekday_name_night_unlang": "Saturday Night", 
                "ampm": "PM", 
                "tz": "", 
                "age": "", 
                "UTCDATE": ""
            }, 
            "temp": {
                "english": "37", 
                "metric": "3"
            }, 
            "dewpoint": {
                "english": "36", 
                "metric": "2"
            }, 
            "condition": "Chance of Rain", 
            "icon": "chancerain", 
            "icon_url": "http://icons.wxug.com/i/c/k/nt_chancerain.gif", 
            "fctcode": "12", 
            "sky": "81", 
            "wspd": {
                "english": "5", 
                "metric": "8"
            }, 
            "wdir": {
                "dir": "ESE", 
                "degrees": "120"
            }, 
            "wx": "Showers", 
            "uvi": "0", 
            "humidity": "98", 
            "windchill": {
                "english": "33", 
                "metric": "1"
            }, 
            "heatindex": {
                "english": "-9999", 
                "metric": "-9999"
            }, 
            "feelslike": {
                "english": "33", 
                "metric": "1"
            }, 
            "qpf": {
                "english": "0.0", 
                "metric": "0"
            }, 
            "snow": {
                "english": "0.0", 
                "metric": "0"
            }, 
            "pop": "36", 
            "mslp": {
                "english": "28.92", 
                "metric": "979"
            }
        }, 
        {
            "FCTTIME": {
                "hour": "22", 
                "hour_padded": "22", 
                "min": "00", 
                "min_unpadded": "0", 
                "sec": "0", 
                "year": "2017", 
                "mon": "11", 
                "mon_padded": "11", 
                "mon_abbrev": "Nov", 
                "mday": "11", 
                "mday_padded": "11", 
                "yday": "314", 
                "isdst": "0", 
                "epoch": "1510430400", 
                "pretty": "10:00 PM EET on November 11, 2017", 
                "civil": "10:00 PM", 
                "month_name": "November", 
                "month_name_abbrev": "Nov", 
                "weekday_name": "Saturday", 
                "weekday_name_night": "Saturday Night", 
                "weekday_name_abbrev": "Sat", 
                "weekday_name_unlang": "Saturday", 
                "weekday_name_night_unlang": "Saturday Night", 
                "ampm": "PM", 
                "tz": "", 
                "age": "", 
                "UTCDATE": ""
            }, 
            "temp": {
                "english": "37", 
                "metric": "3"
            }, 
            "dewpoint": {
                "english": "36", 
                "metric": "2"
            }, 
            "condition": "Chance of Rain", 
            "icon": "chancerain", 
            "icon_url": "http://icons.wxug.com/i/c/k/nt_chancerain.gif", 
            "fctcode": "12", 
            "sky": "82", 
            "wspd": {
                "english": "5", 
                "metric": "8"
            }, 
            "wdir": {
                "dir": "ESE", 
                "degrees": "118"
            }, 
            "wx": "Showers", 
            "uvi": "0", 
            "humidity": "98", 
            "windchill": {
                "english": "33", 
                "metric": "1"
            }, 
            "heatindex": {
                "english": "-9999", 
                "metric": "-9999"
            }, 
            "feelslike": {
                "english": "33", 
                "metric": "1"
            }, 
            "qpf": {
                "english": "0.0", 
                "metric": "0"
            }, 
            "snow": {
                "english": "0.0", 
                "metric": "0"
            }, 
            "pop": "35", 
            "mslp": {
                "english": "28.92", 
                "metric": "979"
            }
        }, 
        {
            "FCTTIME": {
                "hour": "23", 
                "hour_padded": "23", 
                "min": "00", 
                "min_unpadded": "0", 
                "sec": "0", 
                "year": "2017", 
                "mon": "11", 
                "mon_padded": "11", 
                "mon_abbrev": "Nov", 
                "mday": "11", 
                "mday_padded": "11", 
                "yday": "314", 
                "isdst": "0", 
                "epoch": "1510434000", 
                "pretty": "11:00 PM EET on November 11, 2017", 
                "civil": "11:00 PM", 
                "month_name": "November", 
                "month_name_abbrev": "Nov", 
                "weekday_name": "Saturday", 
                "weekday_name_night": "Saturday Night", 
                "weekday_name_abbrev": "Sat", 
                "weekday_name_unlang": "Saturday", 
                "weekday_name_night_unlang": "Saturday Night", 
                "ampm": "PM", 
                "tz": "", 
                "age": "", 
                "UTCDATE": ""
            }, 
            "temp": {
                "english": "36", 
                "metric": "2"
            }, 
            "dewpoint": {
                "english": "35", 
                "metric": "2"
            }, 
            "condition": "Chance of Rain", 
            "icon": "chancerain", 
            "icon_url": "http://icons.wxug.com/i/c/k/nt_chancerain.gif", 
            "fctcode": "12", 
            "sky": "83", 
            "wspd": {
                "english": "4", 
                "metric": "6"
            }, 
            "wdir": {
                "dir": "ESE", 
                "degrees": "113"
            }, 
            "wx": "Showers", 
            "uvi": "0", 
            "humidity": "97", 
            "windchill": {
                "english": "32", 
                "metric": "0"
            }, 
            "heatindex": {
                "english": "-9999", 
                "metric": "-9999"
            }, 
            "feelslike": {
                "english": "32", 
                "metric": "0"
            }, 
            "qpf": {
                "english": "0.01", 
                "metric": "0"
            }, 
            "snow": {
                "english": "0.0", 
                "metric": "0"
            }, 
            "pop": "36", 
            "mslp": {
                "english": "28.91", 
                "metric": "979"
            }
        }, 
        {
            "FCTTIME": {
                "hour": "0", 
                "hour_padded": "00", 
                "min": "00", 
                "min_unpadded": "0", 
                "sec": "0", 
                "year": "2017", 
                "mon": "11", 
                "mon_padded": "11", 
                "mon_abbrev": "Nov", 
                "mday": "12", 
                "mday_padded": "12", 
                "yday": "315", 
                "isdst": "0", 
                "epoch": "1510437600", 
                "pretty": "12:00 AM EET on November 12, 2017", 
                "civil": "12:00 AM", 
                "month_name": "November", 
                "month_name_abbrev": "Nov", 
                "weekday_name": "Sunday", 
                "weekday_name_night": "Sunday Night", 
                "weekday_name_abbrev": "Sun", 
                "weekday_name_unlang": "Sunday", 
                "weekday_name_night_unlang": "Sunday Night", 
                "ampm": "AM", 
                "tz": "", 
                "age": "", 
                "UTCDATE": ""
            }, 
            "temp": {
                "english": "36", 
                "metric": "2"
            }, 
            "dewpoint": {
                "english": "35", 
                "metric": "2"
            }, 
            "condition": "Chance of Rain", 
            "icon": "chancerain", 
            "icon_url": "http://icons.wxug.com/i/c/k/nt_chancerain.gif", 
            "fctcode": "12", 
            "sky": "84", 
            "wspd": {
                "english": "4", 
                "metric": "6"
            }, 
            "wdir": {
                "dir": "ESE", 
                "degrees": "109"
            }, 
            "wx": "Showers", 
            "uvi": "0", 
            "humidity": "97", 
            "windchill": {
                "english": "32", 
                "metric": "0"
            }, 
            "heatindex": {
                "english": "-9999", 
                "metric": "-9999"
            }, 
            "feelslike": {
                "english": "32", 
                "metric": "0"
            }, 
            "qpf": {
                "english": "0.01", 
                "metric": "0"
            }, 
            "snow": {
                "english": "0.0", 
                "metric": "0"
            }, 
            "pop": "38", 
            "mslp": {
                "english": "28.9", 
                "metric": "979"
            }
        }
    ]
}